[
    {
        "key": "dbln",
        "value": "%7B%2261568068416080%22%3A%22sYbEGhu6%22%2C%2261571471747649%22%3A%22ck8UV3Nh%22%2C%2261570967284501%22%3A%22ecQkn1Ft%22%2C%22100078299405598%22%3A%227nBKT7Qq%22%2C%2261572003177039%22%3A%22Pjy42bLK%22%7D",
        "domain": "facebook.com",
        "path": "/login/device-based/",
        "hostOnly": false,
        "creation": "2025-07-06T06:30:13.447Z",
        "lastAccessed": "2025-07-06T06:30:13.449Z"
    },
    {
        "key": "datr",
        "value": "NTc6aDnWjjclgAIuGaYgNONM",
        "domain": "facebook.com",
        "path": "/",
        "hostOnly": false,
        "creation": "2025-07-06T06:30:13.449Z",
        "lastAccessed": "2025-07-06T06:30:13.449Z"
    },
    {
        "key": "sb",
        "value": "fTc6aBV2qHXSfLYkDfNuMRXf",
        "domain": "facebook.com",
        "path": "/",
        "hostOnly": false,
        "creation": "2025-07-06T06:30:13.449Z",
        "lastAccessed": "2025-07-06T06:30:13.449Z"
    },
    {
        "key": "vpd",
        "value": "v1%3B664x360x2",
        "domain": "facebook.com",
        "path": "/",
        "hostOnly": false,
        "creation": "2025-07-06T06:30:13.449Z",
        "lastAccessed": "2025-07-06T06:30:13.449Z"
    },
    {
        "key": "ps_l",
        "value": "1",
        "domain": "facebook.com",
        "path": "/",
        "hostOnly": false,
        "creation": "2025-07-06T06:30:13.449Z",
        "lastAccessed": "2025-07-06T06:30:13.449Z"
    },
    {
        "key": "ps_n",
        "value": "1",
        "domain": "facebook.com",
        "path": "/",
        "hostOnly": false,
        "creation": "2025-07-06T06:30:13.449Z",
        "lastAccessed": "2025-07-06T06:30:13.449Z"
    },
    {
        "key": "c_user",
        "value": "61572003177039",
        "domain": "facebook.com",
        "path": "/",
        "hostOnly": false,
        "creation": "2025-07-06T06:30:13.449Z",
        "lastAccessed": "2025-07-06T06:30:13.449Z"
    },
    {
        "key": "xs",
        "value": "28%3AT9ZHYPhpP_kzWg%3A2%3A1750613025%3A-1%3A-1",
        "domain": "facebook.com",
        "path": "/",
        "hostOnly": false,
        "creation": "2025-07-06T06:30:13.449Z",
        "lastAccessed": "2025-07-06T06:30:13.449Z"
    },
    {
        "key": "pas",
        "value": "61572003177039%3AWrZzp9nG5J",
        "domain": "facebook.com",
        "path": "/",
        "hostOnly": false,
        "creation": "2025-07-06T06:30:13.449Z",
        "lastAccessed": "2025-07-06T06:30:13.449Z"
    },
    {
        "key": "locale",
        "value": "en_GB",
        "domain": "facebook.com",
        "path": "/",
        "hostOnly": false,
        "creation": "2025-07-06T06:30:13.450Z",
        "lastAccessed": "2025-07-06T06:30:13.450Z"
    },
    {
        "key": "fr",
        "value": "0JkBmguVFoti4E64t.AWedvA6eMpcardhgkmLgjht6nbJNpmDZng5I03A17_FYI9-U8g8.BoVRk1..AAA.0.0.Boahfv.AWdVC12bNFIRFYhu3bU5FQCGZQs",
        "domain": "facebook.com",
        "path": "/",
        "hostOnly": false,
        "creation": "2025-07-06T06:30:13.450Z",
        "lastAccessed": "2025-07-06T06:30:13.450Z"
    },
    {
        "key": "fbl_st",
        "value": "101238224%3BT%3A29196390",
        "domain": "facebook.com",
        "path": "/",
        "hostOnly": false,
        "creation": "2025-07-06T06:30:13.450Z",
        "lastAccessed": "2025-07-06T06:30:13.450Z"
    },
    {
        "key": "wl_cbv",
        "value": "v2%3Bclient_version%3A2860%3Btimestamp%3A1751783407",
        "domain": "facebook.com",
        "path": "/",
        "hostOnly": false,
        "creation": "2025-07-06T06:30:13.450Z",
        "lastAccessed": "2025-07-06T06:30:13.450Z"
    }
]
